rmsfact/__init__.py
rmsfact/__main__.py
rmsfact/new_rmsfact.py
rmsfact/data/rmsfact.dat
rmsfact/data/rmsfact.txt
rmsfact-0.4.1.dist-info/LICENSE
rmsfact-0.4.1.dist-info/METADATA
rmsfact-0.4.1.dist-info/WHEEL
rmsfact-0.4.1.dist-info/top_level.txt
rmsfact-0.4.1.dist-info/RECORD
