Metadata-Version: 2.1
Name: rmsfact
Version: 0.4.1
Summary: Display a randomly selected quote about Richard M. Stallman.
Home-page: https://www.github.com/lewinfox/rmsfact
Author: Lewin Appleton-Fox
Author-email: lewin.a.f@gmail.com
License: UNKNOWN
Project-URL: Issues, https://www.github.com/lewinfox/rmsfact/issues
Platform: UNKNOWN
Classifier: Programming Language :: Python :: 3
Classifier: License :: OSI Approved :: GNU General Public License v3 (GPLv3)
Classifier: Operating System :: OS Independent
Requires-Python: >=3.6
